rpg_handbook/__init__.py
rpg_handbook/__main__.py
rpg_handbook/commands/__init__.py
rpg_handbook/commands/strip-hi.py
rpg_handbook/commands/version.py
rpg_handbook/constants.py
rpg_handbook-0.1.0.dist-info/entry_points.txt
rpg_handbook-0.1.0.dist-info/WHEEL
rpg_handbook-0.1.0.dist-info/METADATA
rpg_handbook-0.1.0.dist-info/RECORD
