Metadata-Version: 2.1
Name: rpg-handbook
Version: 0.1.0
Summary: Peer-to-Peer DVD Remuxing Rules by -RPG.
Home-page: https://github.com/rlaphoenix/RPG
Author: rlaphoenix
Author-email: rlaphoenix@pm.me
Requires-Python: >=3.7,<4.0
Classifier: Programming Language :: Python :: 3
Classifier: Programming Language :: Python :: 3.10
Classifier: Programming Language :: Python :: 3.7
Classifier: Programming Language :: Python :: 3.8
Classifier: Programming Language :: Python :: 3.9
Provides-Extra: docs
Requires-Dist: Sphinx (>=4.4.0,<5.0.0); extra == "docs"
Requires-Dist: appdirs (>=1.4.4,<2.0.0)
Requires-Dist: click (>=8.0.4,<9.0.0)
Requires-Dist: furo (>=2022.3.4,<2023.0.0); extra == "docs"
Requires-Dist: m2r2 (>=0.3.2,<0.4.0); extra == "docs"
Requires-Dist: sphinxcontrib-images (>=0.9.4,<0.10.0); extra == "docs"
Requires-Dist: subtitle-filter (>=1.4.3,<2.0.0)
Requires-Dist: tqdm (>=4.63.0,<5.0.0)
Project-URL: Repository, https://github.com/rlaphoenix/RPG
